lost_cat/__init__.py
lost_cat/lost_cat.py
lost_cat/actions/__init__.py
lost_cat/actions/base_actions.py
lost_cat/database/__init__.py
lost_cat/database/db_utils.py
lost_cat/database/schema.py
lost_cat/examples/run_rules.py
lost_cat/parsers/__init__.py
lost_cat/parsers/base_parser.py
lost_cat/parsers/zip_parser.py
lost_cat/processors/__init__.py
lost_cat/processors/base_processor.py
lost_cat/processors/filesystem_scanner.py
lost_cat/ui/__init__.py
lost_cat/utils/__init__.py
lost_cat/utils/module_utils.py
lost_cat/utils/path_utils.py
lost_cat/utils/phrase_utils.py
lost_cat/utils/rules_utils.py
lost_cat/utils/tag_anon.py
lost_cat/utils/text_utils.py
lost_cat/utils/trie_utils.py
lost_cat-0.1.9.dist-info/LICENSE
lost_cat-0.1.9.dist-info/METADATA
lost_cat-0.1.9.dist-info/WHEEL
lost_cat-0.1.9.dist-info/top_level.txt
lost_cat-0.1.9.dist-info/RECORD
