Metadata-Version: 2.1
Name: lost_cat
Version: 0.1.9
Summary: Lost cat is a package to scan a variety of locations and report back the files, metadata, and summary contents as needed.
Author-email: Dreffed aka David Gloyn-Cox <dreffed@gmail.com>, Thoughtswin Systems Inc <david.gloyn-cox@thoughtswinsystems.com>
License: MIT License
Project-URL: Homepage, https://github.com/thoughtswinsystems/lost-cat
Project-URL: Bug Tracker, https://github.com/thoughtswinsystems/lost-cat/issues
Classifier: Programming Language :: Python :: 3
Classifier: License :: OSI Approved :: MIT License
Classifier: Operating System :: OS Independent
Requires-Python: >=3.8
License-File: LICENSE
Requires-Dist: nltk
Requires-Dist: numpy
Requires-Dist: pillow
Requires-Dist: sqlalchemy
Requires-Dist: psutil
Requires-Dist: pyodbc
Requires-Dist: python-dotenv
Requires-Dist: validators
